setup.py
binstar.egg-info/PKG-INFO
binstar.egg-info/SOURCES.txt
binstar.egg-info/dependency_links.txt
binstar.egg-info/entry_points.txt
binstar.egg-info/requires.txt
binstar.egg-info/top_level.txt
binstar_client/__init__.py
binstar_client/_version.py
binstar_client/errors.py
binstar_client/pprintb.py
binstar_client/requests_ext.py
binstar_client/commands/__init__.py
binstar_client/commands/_files.py
binstar_client/commands/_release.py
binstar_client/commands/authorizations.py
binstar_client/commands/channel.py
binstar_client/commands/config.py
binstar_client/commands/copy.py
binstar_client/commands/groups.py
binstar_client/commands/login.py
binstar_client/commands/logout.py
binstar_client/commands/package.py
binstar_client/commands/remove.py
binstar_client/commands/search.py
binstar_client/commands/show.py
binstar_client/commands/upload.py
binstar_client/commands/whoami.py
binstar_client/inspect_package/__init__.py
binstar_client/inspect_package/conda.py
binstar_client/inspect_package/conda_installer.py
binstar_client/inspect_package/ipynb.py
binstar_client/inspect_package/pypi.py
binstar_client/inspect_package/r.py
binstar_client/inspect_package/uitls.py
binstar_client/inspect_package/tests/__init__.py
binstar_client/inspect_package/tests/test_conda.py
binstar_client/inspect_package/tests/test_pypi.py
binstar_client/mixins/__init__.py
binstar_client/mixins/channels.py
binstar_client/mixins/organizations.py
binstar_client/mixins/package.py
binstar_client/scripts/__init__.py
binstar_client/scripts/cli.py
binstar_client/tests/__init__.py
binstar_client/tests/coverage_report.py
binstar_client/tests/fixture.py
binstar_client/tests/runner.py
binstar_client/tests/runtests.py
binstar_client/tests/test_ipynb.py
binstar_client/tests/test_login.py
binstar_client/tests/test_register.py
binstar_client/tests/test_upload.py
binstar_client/tests/test_whoami.py
binstar_client/tests/urlmock.py
binstar_client/utils/__init__.py
binstar_client/utils/appdirs.py
binstar_client/utils/detect.py
binstar_client/utils/handlers.py
binstar_client/utils/http_codes.py
binstar_client/utils/pprint.py