Metadata-Version: 1.0
Name: binstar
Version: 0.10.4
Summary: Binstar command line client library
Home-page: http://github.com/Binstar/binstar_client
Author: Sean Ross-Ross
Author-email: srossross@gmail.com
License: UNKNOWN
Platform: UNKNOWN
